pocket_dimension/__init__.py
pocket_dimension/random_projection.py
pocket_dimension/vectorizer.py
pocket_dimension-0.2.0.dist-info/licenses/LICENSE
pocket_dimension-0.2.0.dist-info/METADATA
pocket_dimension-0.2.0.dist-info/WHEEL
pocket_dimension-0.2.0.dist-info/top_level.txt
pocket_dimension-0.2.0.dist-info/RECORD
