Metadata-Version: 2.4
Name: pocket_dimension
Version: 0.2.0
Summary: Memory-efficient, dense, random projection of sparse vectors.
Author-email: Matthew Hendrey <matthew.hendrey@gmail.com>
License-Expression: GPL-3.0-only
Project-URL: Documentation, https://mhendrey.github.io/pocket_dimension
Project-URL: Source, https://github.com/mhendrey/pocket_dimension
Keywords: numba,random projection,term-frequency,tfidf,dimension reduction
Requires-Python: >=3.11
License-File: LICENSE
Requires-Dist: numba>=0.55.2
Requires-Dist: pybloomfiltermmap3>=0.5.5
Requires-Dist: scikit-learn>=1.6
Requires-Dist: sketchnu>=1.2
Dynamic: license-file
